epss/__init__.py
epss/cli.py
epss/epss.py
epss-0.1.1.dist-info/AUTHORS.rst
epss-0.1.1.dist-info/LICENSE
epss-0.1.1.dist-info/METADATA
epss-0.1.1.dist-info/WHEEL
epss-0.1.1.dist-info/entry_points.txt
epss-0.1.1.dist-info/top_level.txt
epss-0.1.1.dist-info/RECORD
