Metadata-Version: 2.1
Name: epss
Version: 0.1.1
Summary: A pandas friendly library for the EPSS.
Home-page: https://github.com/priamai/epss
Author: Paolo Di Prodi
Author-email: paolo@priam.ai
License: Apache Software License 2.0
Keywords: epss
Platform: UNKNOWN
Classifier: Development Status :: 2 - Pre-Alpha
Classifier: Intended Audience :: Developers
Classifier: License :: OSI Approved :: Apache Software License
Classifier: Natural Language :: English
Classifier: Programming Language :: Python :: 3
Classifier: Programming Language :: Python :: 3.6
Classifier: Programming Language :: Python :: 3.7
Classifier: Programming Language :: Python :: 3.8
Requires-Python: >=3.6
Requires-Dist: Click (>=7.0)
